models/Restormer.py
models/SpachTransformer.py
models/SwinTransformer.py
models/__init__.py
spach_transformer-0.1.1.dist-info/METADATA
spach_transformer-0.1.1.dist-info/WHEEL
spach_transformer-0.1.1.dist-info/top_level.txt
spach_transformer-0.1.1.dist-info/RECORD
