Metadata-Version: 2.1
Name: spach-transformer
Version: 0.1.1
Summary: A package for SpachTransformer and related models
Home-page: https://github.com/sijang/SpachTransformer
Author: sijang
Author-email: sein.jang@yale.edu
Classifier: Programming Language :: Python :: 3
Classifier: License :: OSI Approved :: MIT License
Classifier: Operating System :: OS Independent
Requires-Python: >=3.6
Requires-Dist: torch >=1.10.1
Requires-Dist: torchvision >=0.11.2
Requires-Dist: torchaudio >=0.10.1
Requires-Dist: numpy >=1.21.2
Requires-Dist: scipy >=1.7.3
Requires-Dist: h5py >=3.6.0
Requires-Dist: imageio >=2.13.5
Requires-Dist: matplotlib >=3.5.1
Requires-Dist: scikit-image >=0.19.1
Requires-Dist: scikit-learn >=1.0.2
Requires-Dist: simpleitk >=2.2.1
Requires-Dist: tqdm >=4.62.3
Requires-Dist: opencv-python >=4.5.5.62
Requires-Dist: pyyaml >=6.0
Requires-Dist: timm >=0.4.12
Requires-Dist: einops >=0.3.2
Requires-Dist: torchmetrics >=0.11.0
Requires-Dist: yacs >=0.1.8
Requires-Dist: networkx >=2.6.3
Requires-Dist: joblib >=1.1.0
